Metadata-Version: 1.0
Name: musicbutler
Version: 0.1.7
Summary: A robot that receives voice commands to play albums from your MP3 collection
Home-page: http://musicbutler.googlecode.com/
Author: Michael Gundlach
Author-email: gundlach@gmail.com
License: UNKNOWN
Keywords: speech recognition music stereo control mp3 robot butler
Platform: UNKNOWN
Classifier: Development Status :: 3 - Alpha
Classifier: Environment :: Win32 (MS Windows)
Classifier: License :: OSI Approved :: Apache Software License
Classifier: Operating System :: Microsoft :: Windows
Classifier: Programming Language :: Python
Classifier: Topic :: Multimedia :: Sound/Audio :: Speech
Classifier: Topic :: Multimedia :: Sound/Audio
Classifier: Topic :: Home Automation
Classifier: Topic :: Scientific/Engineering :: Human Machine Interfaces
Classifier: Topic :: Software Development :: Libraries :: Python Modules
Classifier: Topic :: Desktop Environment
